src/__init__.py
src/app.py
src/logger.py
src/plugins/__init__.py
src/plugins/encryptions/__init__.py
src/plugins/encryptions/basic.py
src/plugins/secrets/1password.py
src/plugins/secrets/__init__.py
src/plugins/secrets/bitwarden.py
src/plugins/secrets/pass.py
secret_template_renderer-0.2.3.dist-info/LICENSE
secret_template_renderer-0.2.3.dist-info/METADATA
secret_template_renderer-0.2.3.dist-info/WHEEL
secret_template_renderer-0.2.3.dist-info/entry_points.txt
secret_template_renderer-0.2.3.dist-info/RECORD
