Metadata-Version: 2.3
Name: secret_template_renderer
Version: 0.2.3
Summary: A tool for templating .env files and more.
Keywords: template,management,jinja2,secrets,dotenv,.env
Author: Ben Trinh
Author-email: huantrinh1802@gmail.com
Requires-Python: >=3.12,<4.0
Classifier: Programming Language :: Python :: 3
Classifier: Programming Language :: Python :: 3.12
Classifier: Programming Language :: Python :: 3.13
Provides-Extra: crypto
Requires-Dist: jinja2 (>=3.1.5,<4.0.0)
Project-URL: Homepage, https://github.com/huantrinh1802/secret_template_renderer
Project-URL: Issues, https://github.com/huantrinh1802/secret_template_renderer/issues
